openhgnn/__init__.py
openhgnn/config.ini
openhgnn/config.py
openhgnn/experiment.py
openhgnn/auto/__init__.py
openhgnn/auto/hpo.py
openhgnn/auto/hpo_space.py
openhgnn/dataset/EdgeClassificationDataset.py
openhgnn/dataset/HypergraphDataset.py
openhgnn/dataset/LinkPredictionDataset.py
openhgnn/dataset/New_dataset.py
openhgnn/dataset/NodeClassificationDataset.py
openhgnn/dataset/RecommendationDataset.py
openhgnn/dataset/__init__.py
openhgnn/dataset/academic_graph.py
openhgnn/dataset/adapter.py
openhgnn/dataset/alircd_dataset.py
openhgnn/dataset/base_dataset.py
openhgnn/dataset/gtn_dataset.py
openhgnn/dataset/hgb_dataset.py
openhgnn/dataset/knowledge_graph.py
openhgnn/dataset/mg2vec_dataset.py
openhgnn/dataset/multigraph.py
openhgnn/dataset/ohgb_dataset.py
openhgnn/dataset/utils.py
openhgnn/layers/EmbedLayer.py
openhgnn/layers/GeneralGNNLayer.py
openhgnn/layers/GeneralHGNNLayer.py
openhgnn/layers/HeteroGraphConv.py
openhgnn/layers/HeteroLinear.py
openhgnn/layers/MetapathConv.py
openhgnn/layers/SkipConnection.py
openhgnn/layers/__init__.py
openhgnn/layers/macro_layer/ATTConv.py
openhgnn/layers/macro_layer/SemanticConv.py
openhgnn/layers/macro_layer/__init__.py
openhgnn/layers/micro_layer/CompConv.py
openhgnn/layers/micro_layer/HGConv.py
openhgnn/layers/micro_layer/LSTM_conv.py
openhgnn/layers/micro_layer/__init__.py
openhgnn/models/CompGCN.py
openhgnn/models/DHNE.py
openhgnn/models/DMGI.py
openhgnn/models/GATNE.py
openhgnn/models/GIE.py
openhgnn/models/GTN_sparse.py
openhgnn/models/HAN.py
openhgnn/models/HDE.py
openhgnn/models/HGAT.py
openhgnn/models/HGConv.py
openhgnn/models/HGNN_AC.py
openhgnn/models/HGSL.py
openhgnn/models/HGT.py
openhgnn/models/HGT_hetero.py
openhgnn/models/HPN.py
openhgnn/models/HeCo.py
openhgnn/models/HeGAN.py
openhgnn/models/HetGNN.py
openhgnn/models/HetSANN.py
openhgnn/models/HeteroMLP.py
openhgnn/models/KGCN.py
openhgnn/models/MAGNN.py
openhgnn/models/MHNF.py
openhgnn/models/Mg2vec.py
openhgnn/models/Micro_layer.py
openhgnn/models/Multi_level.py
openhgnn_Zihao-0.6.1.dist-info/LICENSE
openhgnn_Zihao-0.6.1.dist-info/METADATA
openhgnn_Zihao-0.6.1.dist-info/WHEEL
openhgnn_Zihao-0.6.1.dist-info/top_level.txt
openhgnn_Zihao-0.6.1.dist-info/RECORD
